data/__init__.py
module/__init__.py
module/module.py
deploy_module-0.1.dist-info/LICENSE
deploy_module-0.1.dist-info/METADATA
deploy_module-0.1.dist-info/WHEEL
deploy_module-0.1.dist-info/top_level.txt
deploy_module-0.1.dist-info/RECORD
